Texas_Extraction/__init__.py
Texas_Extraction/core.py
Texas_Extraction/helper/Queries.py
Texas_Extraction/helper/__init__.py
Texas_Extraction/helper/config.py
Texas_Extraction/services/ChunkProcessor.py
Texas_Extraction/services/MainProcessor.py
Texas_Extraction/services/OracleConnection.py
Texas_Extraction/services/PDFParser.py
Texas_Extraction/services/RequestsService.py
Texas_Extraction/services/RetryLogic.py
Texas_Extraction/services/__init__.py
Texas_Extraction/utils/DataUtils.py
Texas_Extraction/utils/FileTools.py
Texas_Extraction/utils/__init__.py
Texas_Extraction-0.1.2.dist-info/METADATA
Texas_Extraction-0.1.2.dist-info/WHEEL
Texas_Extraction-0.1.2.dist-info/entry_points.txt
Texas_Extraction-0.1.2.dist-info/top_level.txt
Texas_Extraction-0.1.2.dist-info/RECORD
