Metadata-Version: 2.1
Name: Texas_Extraction
Version: 0.1.2
Summary: Extract structured data from PDFs linked in Excel sheets.
Author: Hamdi Emad
Requires-Dist: pandas
Requires-Dist: PyMuPDF
Requires-Dist: requests
